molecule_plugins/__init__.py
molecule_plugins/_version.py
molecule_plugins/py.typed
molecule_plugins/azure/__init__.py
molecule_plugins/azure/driver.py
molecule_plugins/azure/cookiecutter/cookiecutter.json
molecule_plugins/azure/cookiecutter/{{cookiecutter.molecule_directory}}/{{cookiecutter.scenario_name}}/INSTALL.rst
molecule_plugins/azure/cookiecutter/{{cookiecutter.molecule_directory}}/{{cookiecutter.scenario_name}}/converge.yml
molecule_plugins/azure/cookiecutter/{{cookiecutter.molecule_directory}}/{{cookiecutter.scenario_name}}/create.yml
molecule_plugins/azure/cookiecutter/{{cookiecutter.molecule_directory}}/{{cookiecutter.scenario_name}}/destroy.yml
molecule_plugins/containers/__init__.py
molecule_plugins/containers/driver.py
molecule_plugins/containers/cookiecutter/cookiecutter.json
molecule_plugins/containers/cookiecutter/{{cookiecutter.molecule_directory}}/{{cookiecutter.scenario_name}}/converge.yml
molecule_plugins/docker/__init__.py
molecule_plugins/docker/driver.py
molecule_plugins/docker/cookiecutter/cookiecutter.json
molecule_plugins/docker/cookiecutter/{{cookiecutter.molecule_directory}}/{{cookiecutter.scenario_name}}/converge.yml
molecule_plugins/docker/playbooks/Dockerfile.j2
molecule_plugins/docker/playbooks/create.yml
molecule_plugins/docker/playbooks/destroy.yml
molecule_plugins/docker/playbooks/validate-dockerfile.yml
molecule_plugins/docker/playbooks/filter_plugins/get_docker_networks.py
molecule_plugins/docker/playbooks/tasks/create_network.yml
molecule_plugins/docker/playbooks/tasks/delete_network.yml
molecule_plugins/ec2/__init__.py
molecule_plugins/ec2/driver.py
molecule_plugins/ec2/cookiecutter/cookiecutter.json
molecule_plugins/ec2/cookiecutter/{{cookiecutter.molecule_directory}}/{{cookiecutter.scenario_name}}/INSTALL.rst
molecule_plugins/ec2/cookiecutter/{{cookiecutter.molecule_directory}}/{{cookiecutter.scenario_name}}/converge.yml
molecule_plugins-23.6.0.dist-info/LICENSE
molecule_plugins-23.6.0.dist-info/METADATA
molecule_plugins-23.6.0.dist-info/WHEEL
molecule_plugins-23.6.0.dist-info/entry_points.txt
molecule_plugins-23.6.0.dist-info/top_level.txt
molecule_plugins-23.6.0.dist-info/RECORD
